README.rst
setup.py
flask_io/__init__.py
flask_io/actions.py
flask_io/authentication.py
flask_io/errors.py
flask_io/fields.py
flask_io/io.py
flask_io/mimetypes.py
flask_io/negotiation.py
flask_io/parsers.py
flask_io/permissions.py
flask_io/renderers.py
flask_io/tracing.py
flask_io/utils.py
flask_io/validate.py
flask_io.egg-info/PKG-INFO
flask_io.egg-info/SOURCES.txt
flask_io.egg-info/dependency_links.txt
flask_io.egg-info/requires.txt
flask_io.egg-info/top_level.txt