Metadata-Version: 1.1
Name: flask-io
Version: 1.10.2
Summary: Flask-IO is a library for parsing Flask request arguments into parameters and for serialization of complex objects into Flask response.
Home-page: https://github.com/viniciuschiele/flask-io
Author: Vinicius Chiele
Author-email: vinicius.chiele@gmail.com
License: MIT
Keywords: flask,rest,parse,encode,decode,request,json,marshmallow
Platform: UNKNOWN
Classifier: Development Status :: 5 - Production/Stable
Classifier: Intended Audience :: Developers
Classifier: Natural Language :: English
Classifier: Operating System :: OS Independent
Classifier: Programming Language :: Python
Classifier: Programming Language :: Python :: 3
Classifier: Programming Language :: Python :: 3.2
Classifier: Programming Language :: Python :: 3.3
Classifier: Programming Language :: Python :: 3.4
Classifier: Programming Language :: Python :: Implementation :: CPython
